diag2python.cpython-39-x86_64-linux-gnu.so
gsidiag/__main__.py
gsidiag/datasources.py
gsidiag/table
gsidiag/__init__.py
readDiag-2.0.1.dist-info/top_level.txt
readDiag-2.0.1.dist-info/METADATA
readDiag-2.0.1.dist-info/RECORD
readDiag-2.0.1.dist-info/WHEEL
readDiag-2.0.1.dist-info/LICENSE.md
readDiag.libs/libquadmath-2d0c479f.so.0.0.0
readDiag.libs/libgfortran-2e0d59d6.so.5.0.0
